pycheck/__init__.py
pycheck/checker.py
pycheck/cli.py
pycheck/utils.py
pycheck_tool-0.1.4.dist-info/METADATA
pycheck_tool-0.1.4.dist-info/WHEEL
pycheck_tool-0.1.4.dist-info/entry_points.txt
pycheck_tool-0.1.4.dist-info/top_level.txt
pycheck_tool-0.1.4.dist-info/RECORD
